{"id":116,"date":"2023-10-12T10:16:21","date_gmt":"2023-10-12T10:16:21","guid":{"rendered":"https:\/\/designer1.zarin.solutions\/?page_id=116"},"modified":"2023-10-14T06:13:14","modified_gmt":"2023-10-14T06:13:14","slug":"breakfast","status":"publish","type":"page","link":"https:\/\/designer1.zarin.solutions\/?page_id=116","title":{"rendered":"Breakfast"},"content":{"rendered":"\n  <div id=\"page-header-1488909171\" class=\"page-header-wrapper\">\n  <div class=\"page-title dark featured-title\">\n\n        <div class=\"page-title-bg\">\n      <div class=\"title-bg fill bg-fill\"\n        data-parallax-container=\".page-title\"\n        data-parallax-background\n        data-parallax=\"-\">\n      <\/div>\n      <div class=\"title-overlay fill\"><\/div>\n    <\/div>\n    \n    <div class=\"page-title-inner container align-center flex-row medium-flex-wrap\" >\n              <div class=\"title-wrapper flex-col text-left medium-text-center\">\n          <h1 class=\"entry-title mb-0\">\n            Breakfast          <\/h1>\n        <\/div>\n                    <div class=\"title-content flex-col flex-right text-right medium-text-center\">\n        <div class=\"title-breadcrumbs pb-half pt-half\"><\/div>      <\/div>\n    <\/div>\n\n     \n<style>\n#page-header-1488909171 .title-bg {\n  background-image: url(https:\/\/designer1.zarin.solutions\/wp-content\/uploads\/2023\/10\/New-Project-46.png);\n}\n#page-header-1488909171 .title-overlay {\n  background-color: rgba(0,0,0,.5);\n}\n<\/style>\n  <\/div>\n    <\/div>\n  \n\n\t<section class=\"section\" id=\"section_1721477891\">\n\t\t<div class=\"bg section-bg fill bg-fill  bg-loaded\" >\n\n\t\t\t\n\t\t\t\n\t\t\t\n\n\t\t<\/div>\n\n\t\t\n\n\t\t<div class=\"section-content relative\">\n\t\t\t\n\n\t<div id=\"gap-1806563022\" class=\"gap-element clearfix\" style=\"display:block; height:auto;\">\n\t\t\n<style>\n#gap-1806563022 {\n  padding-top: 30px;\n}\n<\/style>\n\t<\/div>\n\t\n\n<div class=\"container section-title-container\" ><h1 class=\"section-title section-title-center\"><b><\/b><span class=\"section-title-main\" style=\"color:rgb(255, 153, 0);\">Breakfast<\/span><b><\/b><\/h1><\/div>\n\n<div class=\"row\"  id=\"row-1230008839\">\n\n\n\t<div id=\"col-200039515\" class=\"col medium-4 small-6 large-4 col-hover-focus\"  data-animate=\"bounceIn\">\n\t\t\t\t<div class=\"col-inner\"  >\n\t\t\t\n\t\t\t\n\n\t<div class=\"box has-hover   has-hover box-text-bottom\" >\n\n\t\t<div class=\"box-image\" style=\"width:75%;\">\n\t\t\t<a href=\"https:\/\/api.whatsapp.com\/send?phone=+923286060257&text=Hello!%20Pind%20Da%20Zaika.%20Sir%20French%20Toast%20kr%20daee.\"  >\t\t\t<div class=\"image-zoom image-cover\" style=\"padding-top:100%;\">\n\t\t\t\t<img width=\"520\" height=\"520\" src=\"https:\/\/designer1.zarin.solutions\/wp-content\/uploads\/2023\/10\/New-Project-64.png\" class=\"attachment- size-\" alt=\"\" decoding=\"async\" loading=\"lazy\" srcset=\"https:\/\/designer1.zarin.solutions\/wp-content\/uploads\/2023\/10\/New-Project-64.png 520w, https:\/\/designer1.zarin.solutions\/wp-content\/uploads\/2023\/10\/New-Project-64-300x300.png 300w, https:\/\/designer1.zarin.solutions\/wp-content\/uploads\/2023\/10\/New-Project-64-150x150.png 150w\" sizes=\"(max-width: 520px) 100vw, 520px\" \/>\t\t\t\t\t\t\t\t\t\t\t<\/div>\n\t\t\t<\/a>\t\t<\/div>\n\n\t\t<div class=\"box-text text-center\" >\n\t\t\t<div class=\"box-text-inner\">\n\t\t\t\t\n\n\t<div id=\"text-1625985697\" class=\"text\">\n\t\t\n\n<h2 style=\"text-align: center;\">French Toast<\/h2>\n\t\t\n<style>\n#text-1625985697 {\n  font-size: 0.75rem;\n  line-height: 3;\n  text-align: center;\n  color: rgb(0, 0, 0);\n}\n#text-1625985697 > * {\n  color: rgb(0, 0, 0);\n}\n<\/style>\n\t<\/div>\n\t\n\t<div id=\"text-3076845844\" class=\"text\">\n\t\t\n\n<p>Price: Rs.179<\/p>\n\t\t\n<style>\n#text-3076845844 {\n  text-align: center;\n  color: rgb(0, 0, 0);\n}\n#text-3076845844 > * {\n  color: rgb(0, 0, 0);\n}\n<\/style>\n\t<\/div>\n\t\n<a data-animate=\"bounceInUp\" rel=\"noopener noreferrer\" href=\"https:\/\/api.whatsapp.com\/send?phone=+923286060257&#038;text=Hello!%20Pind%20Da%20Zaika.%20Sir%20French%20Toast%20kr%20daee.\" target=\"_blank\" class=\"button success\"  style=\"border-radius:99px;\">\n    <span>Order Now<\/span>\n  <i class=\"icon-shopping-cart\" aria-hidden=\"true\" ><\/i><\/a>\n\n\n\n\t\t\t<\/div>\n\t\t<\/div>\n\t<\/div>\n\t\n\n\t\t<\/div>\n\t\t\t\t\t<\/div>\n\n\t\n\n\t<div id=\"col-1740710051\" class=\"col medium-4 small-6 large-4 col-hover-focus\"  data-animate=\"bounceIn\">\n\t\t\t\t<div class=\"col-inner\"  >\n\t\t\t\n\t\t\t\n\n\t<div class=\"box has-hover   has-hover box-text-bottom\" >\n\n\t\t<div class=\"box-image\" style=\"width:75%;\">\n\t\t\t<a href=\"https:\/\/api.whatsapp.com\/send?phone=+923286060257&text=Hello!%20Pind%20Da%20Zaika.%20Sir%20Fried%20Egg+Paratha%20kr%20daee.\" target=\"_blank\" rel=\"noopener noreferrer\" >\t\t\t<div class=\"image-zoom image-cover\" style=\"padding-top:100%;\">\n\t\t\t\t<img width=\"520\" height=\"520\" src=\"https:\/\/designer1.zarin.solutions\/wp-content\/uploads\/2023\/10\/New-Project-65.png\" class=\"attachment- size-\" alt=\"\" decoding=\"async\" loading=\"lazy\" srcset=\"https:\/\/designer1.zarin.solutions\/wp-content\/uploads\/2023\/10\/New-Project-65.png 520w, https:\/\/designer1.zarin.solutions\/wp-content\/uploads\/2023\/10\/New-Project-65-300x300.png 300w, https:\/\/designer1.zarin.solutions\/wp-content\/uploads\/2023\/10\/New-Project-65-150x150.png 150w\" sizes=\"(max-width: 520px) 100vw, 520px\" \/>\t\t\t\t\t\t\t\t\t\t\t<\/div>\n\t\t\t<\/a>\t\t<\/div>\n\n\t\t<div class=\"box-text text-center\" >\n\t\t\t<div class=\"box-text-inner\">\n\t\t\t\t\n\n\t<div id=\"text-2832007254\" class=\"text\">\n\t\t\n\n<h2><strong>Fried Egg+Paratha<\/strong><\/h2>\n\t\t\n<style>\n#text-2832007254 {\n  font-size: 0.75rem;\n  line-height: 0.75;\n  text-align: center;\n  color: rgb(0, 0, 0);\n}\n#text-2832007254 > * {\n  color: rgb(0, 0, 0);\n}\n<\/style>\n\t<\/div>\n\t\n\t<div id=\"text-3951783907\" class=\"text\">\n\t\t\n\n<p>Price: Rs.169<\/p>\n\t\t\n<style>\n#text-3951783907 {\n  text-align: center;\n  color: rgb(0, 0, 0);\n}\n#text-3951783907 > * {\n  color: rgb(0, 0, 0);\n}\n<\/style>\n\t<\/div>\n\t\n<a data-animate=\"bounceInUp\" rel=\"noopener noreferrer\" href=\"https:\/\/api.whatsapp.com\/send?phone=+923286060257&#038;text=Hello!%20Pind%20Da%20Zaika.%20Sir%20Fried%20Egg+Paratha%20kr%20daee.\" target=\"_blank\" class=\"button success\"  style=\"border-radius:99px;\">\n    <span>Order Now<\/span>\n  <i class=\"icon-shopping-cart\" aria-hidden=\"true\" ><\/i><\/a>\n\n\n\n\t\t\t<\/div>\n\t\t<\/div>\n\t<\/div>\n\t\n\n\t\t<\/div>\n\t\t\t\t\t<\/div>\n\n\t\n\n\t<div id=\"col-922398009\" class=\"col medium-4 small-6 large-4 col-hover-focus\"  data-animate=\"bounceIn\">\n\t\t\t\t<div class=\"col-inner\"  >\n\t\t\t\n\t\t\t\n\n\t<div class=\"box has-hover   has-hover box-text-bottom\" >\n\n\t\t<div class=\"box-image\" style=\"width:75%;\">\n\t\t\t<a href=\"https:\/\/api.whatsapp.com\/send?phone=+923286060257&text=Hello!%20Pind%20Da%20Zaika.%20Sir%20Egg%20Paratha%20kr%20daee.\" target=\"_blank\" rel=\"noopener noreferrer\" >\t\t\t<div class=\"image-zoom image-cover\" style=\"padding-top:100%;\">\n\t\t\t\t<img width=\"520\" height=\"520\" src=\"https:\/\/designer1.zarin.solutions\/wp-content\/uploads\/2023\/10\/New-Project-66.png\" class=\"attachment- size-\" alt=\"\" decoding=\"async\" loading=\"lazy\" srcset=\"https:\/\/designer1.zarin.solutions\/wp-content\/uploads\/2023\/10\/New-Project-66.png 520w, https:\/\/designer1.zarin.solutions\/wp-content\/uploads\/2023\/10\/New-Project-66-300x300.png 300w, https:\/\/designer1.zarin.solutions\/wp-content\/uploads\/2023\/10\/New-Project-66-150x150.png 150w\" sizes=\"(max-width: 520px) 100vw, 520px\" \/>\t\t\t\t\t\t\t\t\t\t\t<\/div>\n\t\t\t<\/a>\t\t<\/div>\n\n\t\t<div class=\"box-text text-center\" >\n\t\t\t<div class=\"box-text-inner\">\n\t\t\t\t\n\n\t<div id=\"text-2193387428\" class=\"text\">\n\t\t\n\n<h2 style=\"text-align: center;\"><strong>Egg Paratha<\/strong><\/h2>\n\t\t\n<style>\n#text-2193387428 {\n  font-size: 0.75rem;\n  line-height: 0.75;\n  text-align: center;\n  color: rgb(0, 0, 0);\n}\n#text-2193387428 > * {\n  color: rgb(0, 0, 0);\n}\n<\/style>\n\t<\/div>\n\t\n\t<div id=\"text-1914567413\" class=\"text\">\n\t\t\n\n<p>Price: Rs.149<\/p>\n\t\t\n<style>\n#text-1914567413 {\n  text-align: center;\n  color: rgb(0, 0, 0);\n}\n#text-1914567413 > * {\n  color: rgb(0, 0, 0);\n}\n<\/style>\n\t<\/div>\n\t\n<a data-animate=\"bounceInUp\" rel=\"noopener noreferrer\" href=\"https:\/\/api.whatsapp.com\/send?phone=+923286060257&#038;text=Hello!%20Pind%20Da%20Zaika.%20Sir%20Egg%20Paratha%20kr%20daee.\" target=\"_blank\" class=\"button success\"  style=\"border-radius:99px;\">\n    <span>Order Now<\/span>\n  <i class=\"icon-shopping-cart\" aria-hidden=\"true\" ><\/i><\/a>\n\n\n\n\t\t\t<\/div>\n\t\t<\/div>\n\t<\/div>\n\t\n\n\t\t<\/div>\n\t\t\t\t\t<\/div>\n\n\t\n\n\t<div id=\"col-1353585402\" class=\"col medium-4 small-6 large-4 col-hover-focus\"  data-animate=\"bounceIn\">\n\t\t\t\t<div class=\"col-inner\"  >\n\t\t\t\n\t\t\t\n\n\t<div class=\"box has-hover   has-hover box-text-bottom\" >\n\n\t\t<div class=\"box-image\" style=\"width:75%;\">\n\t\t\t<a href=\"https:\/\/api.whatsapp.com\/send?phone=+923286060257&text=Hello!%20Pind%20Da%20Zaika.%20Sir%20Simple%20Omelette%20kr%20daee.\" target=\"_blank\" rel=\"noopener noreferrer\" >\t\t\t<div class=\"image-zoom image-cover\" style=\"padding-top:100%;\">\n\t\t\t\t<img width=\"520\" height=\"520\" src=\"https:\/\/designer1.zarin.solutions\/wp-content\/uploads\/2023\/10\/New-Project-67.png\" class=\"attachment- size-\" alt=\"\" decoding=\"async\" loading=\"lazy\" srcset=\"https:\/\/designer1.zarin.solutions\/wp-content\/uploads\/2023\/10\/New-Project-67.png 520w, https:\/\/designer1.zarin.solutions\/wp-content\/uploads\/2023\/10\/New-Project-67-300x300.png 300w, https:\/\/designer1.zarin.solutions\/wp-content\/uploads\/2023\/10\/New-Project-67-150x150.png 150w\" sizes=\"(max-width: 520px) 100vw, 520px\" \/>\t\t\t\t\t\t\t\t\t\t\t<\/div>\n\t\t\t<\/a>\t\t<\/div>\n\n\t\t<div class=\"box-text text-center\" >\n\t\t\t<div class=\"box-text-inner\">\n\t\t\t\t\n\n\t<div id=\"text-1152756614\" class=\"text\">\n\t\t\n\n<h2 style=\"text-align: center;\"><strong>Simple\u00a0<\/strong><b>Omelette<\/b><\/h2>\n\t\t\n<style>\n#text-1152756614 {\n  font-size: 0.75rem;\n  line-height: 0.75;\n  text-align: center;\n  color: rgb(0, 0, 0);\n}\n#text-1152756614 > * {\n  color: rgb(0, 0, 0);\n}\n<\/style>\n\t<\/div>\n\t\n\t<div id=\"text-2105532211\" class=\"text\">\n\t\t\n\n<p>Price: Rs.159<\/p>\n\t\t\n<style>\n#text-2105532211 {\n  text-align: center;\n  color: rgb(0, 0, 0);\n}\n#text-2105532211 > * {\n  color: rgb(0, 0, 0);\n}\n<\/style>\n\t<\/div>\n\t\n<a data-animate=\"bounceInUp\" rel=\"noopener noreferrer\" href=\"https:\/\/api.whatsapp.com\/send?phone=+923286060257&#038;text=Hello!%20Pind%20Da%20Zaika.%20Sir%20Simple%20Omelette%20kr%20daee.\" target=\"_blank\" class=\"button success\"  style=\"border-radius:99px;\">\n    <span>Order Now<\/span>\n  <i class=\"icon-shopping-cart\" aria-hidden=\"true\" ><\/i><\/a>\n\n\n\n\t\t\t<\/div>\n\t\t<\/div>\n\t<\/div>\n\t\n\n\t\t<\/div>\n\t\t\t\t\t<\/div>\n\n\t\n\n\t<div id=\"col-204186941\" class=\"col medium-4 small-6 large-4 col-hover-focus\"  data-animate=\"bounceIn\">\n\t\t\t\t<div class=\"col-inner\"  >\n\t\t\t\n\t\t\t\n\n\t<div class=\"box has-hover   has-hover box-text-bottom\" >\n\n\t\t<div class=\"box-image\" style=\"width:75%;\">\n\t\t\t<a href=\"https:\/\/api.whatsapp.com\/send?phone=+923286060257&text=Hello!%20Pind%20Da%20Zaika.%20Sir%20Special%20Omelette%20kr%20daee.\" target=\"_blank\" rel=\"noopener noreferrer\" >\t\t\t<div class=\"image-zoom image-cover\" style=\"padding-top:100%;\">\n\t\t\t\t<img width=\"520\" height=\"520\" src=\"https:\/\/designer1.zarin.solutions\/wp-content\/uploads\/2023\/10\/New-Project-69.png\" class=\"attachment- size-\" alt=\"\" decoding=\"async\" loading=\"lazy\" srcset=\"https:\/\/designer1.zarin.solutions\/wp-content\/uploads\/2023\/10\/New-Project-69.png 520w, https:\/\/designer1.zarin.solutions\/wp-content\/uploads\/2023\/10\/New-Project-69-300x300.png 300w, https:\/\/designer1.zarin.solutions\/wp-content\/uploads\/2023\/10\/New-Project-69-150x150.png 150w\" sizes=\"(max-width: 520px) 100vw, 520px\" \/>\t\t\t\t\t\t\t\t\t\t\t<\/div>\n\t\t\t<\/a>\t\t<\/div>\n\n\t\t<div class=\"box-text text-center\" >\n\t\t\t<div class=\"box-text-inner\">\n\t\t\t\t\n\n\t<div id=\"text-947021465\" class=\"text\">\n\t\t\n\n<h2 style=\"text-align: center;\"><strong>Special <\/strong><b>Omelette<\/b><\/h2>\n\t\t\n<style>\n#text-947021465 {\n  font-size: 0.75rem;\n  line-height: 0.75;\n  text-align: center;\n  color: rgb(0, 0, 0);\n}\n#text-947021465 > * {\n  color: rgb(0, 0, 0);\n}\n<\/style>\n\t<\/div>\n\t\n\t<div id=\"text-2323891209\" class=\"text\">\n\t\t\n\n<p>Price: Rs.199<\/p>\n\t\t\n<style>\n#text-2323891209 {\n  text-align: center;\n  color: rgb(0, 0, 0);\n}\n#text-2323891209 > * {\n  color: rgb(0, 0, 0);\n}\n<\/style>\n\t<\/div>\n\t\n<a data-animate=\"bounceInUp\" rel=\"noopener noreferrer\" href=\"https:\/\/api.whatsapp.com\/send?phone=+923286060257&#038;text=Hello!%20Pind%20Da%20Zaika.%20Sir%20Special%20Omelette%20kr%20daee.\" target=\"_blank\" class=\"button success\"  style=\"border-radius:99px;\">\n    <span>Order Now<\/span>\n  <i class=\"icon-shopping-cart\" aria-hidden=\"true\" ><\/i><\/a>\n\n\n\n\t\t\t<\/div>\n\t\t<\/div>\n\t<\/div>\n\t\n\n\t\t<\/div>\n\t\t\t\t\t<\/div>\n\n\t\n\n\t<div id=\"col-1646696866\" class=\"col medium-4 small-6 large-4 col-hover-focus\"  data-animate=\"bounceIn\">\n\t\t\t\t<div class=\"col-inner\"  >\n\t\t\t\n\t\t\t\n\n\t<div class=\"box has-hover   has-hover box-text-bottom\" >\n\n\t\t<div class=\"box-image\" style=\"width:75%;\">\n\t\t\t<a href=\"https:\/\/api.whatsapp.com\/send?phone=+923286060257&text=Hello!%20Pind%20Da%20Zaika.%20Sir%20Simple%20Plain%20Paratha%20kr%20daee.\" target=\"_blank\" rel=\"noopener noreferrer\" >\t\t\t<div class=\"image-zoom image-cover\" style=\"padding-top:100%;\">\n\t\t\t\t<img width=\"520\" height=\"520\" src=\"https:\/\/designer1.zarin.solutions\/wp-content\/uploads\/2023\/10\/New-Project-70.png\" class=\"attachment- size-\" alt=\"\" decoding=\"async\" loading=\"lazy\" srcset=\"https:\/\/designer1.zarin.solutions\/wp-content\/uploads\/2023\/10\/New-Project-70.png 520w, https:\/\/designer1.zarin.solutions\/wp-content\/uploads\/2023\/10\/New-Project-70-300x300.png 300w, https:\/\/designer1.zarin.solutions\/wp-content\/uploads\/2023\/10\/New-Project-70-150x150.png 150w\" sizes=\"(max-width: 520px) 100vw, 520px\" \/>\t\t\t\t\t\t\t\t\t\t\t<\/div>\n\t\t\t<\/a>\t\t<\/div>\n\n\t\t<div class=\"box-text text-center\" >\n\t\t\t<div class=\"box-text-inner\">\n\t\t\t\t\n\n\t<div id=\"text-2201552215\" class=\"text\">\n\t\t\n\n<h2 style=\"text-align: center;\">Simple Plain Paratha<\/h2>\n\t\t\n<style>\n#text-2201552215 {\n  font-size: 0.75rem;\n  line-height: 0.75;\n  text-align: center;\n  color: rgb(0, 0, 0);\n}\n#text-2201552215 > * {\n  color: rgb(0, 0, 0);\n}\n<\/style>\n\t<\/div>\n\t\n\t<div id=\"text-1217959955\" class=\"text\">\n\t\t\n\n<p>Price: Rs.49<\/p>\n\t\t\n<style>\n#text-1217959955 {\n  text-align: center;\n  color: rgb(0, 0, 0);\n}\n#text-1217959955 > * {\n  color: rgb(0, 0, 0);\n}\n<\/style>\n\t<\/div>\n\t\n<a data-animate=\"bounceInUp\" rel=\"noopener noreferrer\" href=\"https:\/\/api.whatsapp.com\/send?phone=+923286060257&#038;text=Hello!%20Pind%20Da%20Zaika.%20Sir%20Simple%20Plain%20Paratha%20kr%20daee.\" target=\"_blank\" class=\"button success\"  style=\"border-radius:99px;\">\n    <span>Order Now<\/span>\n  <i class=\"icon-shopping-cart\" aria-hidden=\"true\" ><\/i><\/a>\n\n\n\n\t\t\t<\/div>\n\t\t<\/div>\n\t<\/div>\n\t\n\n\t\t<\/div>\n\t\t\t\t\t<\/div>\n\n\t\n\n\t<div id=\"col-1138693003\" class=\"col medium-4 small-6 large-4 col-hover-focus\"  data-animate=\"bounceIn\">\n\t\t\t\t<div class=\"col-inner\"  >\n\t\t\t\n\t\t\t\n\n\t<div class=\"box has-hover   has-hover box-text-bottom\" >\n\n\t\t<div class=\"box-image\" style=\"width:75%;\">\n\t\t\t<a href=\"https:\/\/api.whatsapp.com\/send?phone=+923286060257&text=Hello!%20Pind%20Da%20Zaika.%20Sir%20Simple%20Roti%20kr%20daee.\" target=\"_blank\" rel=\"noopener noreferrer\" >\t\t\t<div class=\"image-zoom image-cover\" style=\"padding-top:100%;\">\n\t\t\t\t<img width=\"520\" height=\"520\" src=\"https:\/\/designer1.zarin.solutions\/wp-content\/uploads\/2023\/10\/New-Project-71.png\" class=\"attachment- size-\" alt=\"\" decoding=\"async\" loading=\"lazy\" srcset=\"https:\/\/designer1.zarin.solutions\/wp-content\/uploads\/2023\/10\/New-Project-71.png 520w, https:\/\/designer1.zarin.solutions\/wp-content\/uploads\/2023\/10\/New-Project-71-300x300.png 300w, https:\/\/designer1.zarin.solutions\/wp-content\/uploads\/2023\/10\/New-Project-71-150x150.png 150w\" sizes=\"(max-width: 520px) 100vw, 520px\" \/>\t\t\t\t\t\t\t\t\t\t\t<\/div>\n\t\t\t<\/a>\t\t<\/div>\n\n\t\t<div class=\"box-text text-center\" >\n\t\t\t<div class=\"box-text-inner\">\n\t\t\t\t\n\n\t<div id=\"text-1571559023\" class=\"text\">\n\t\t\n\n<h2 style=\"text-align: center;\"><strong>Simple Roti<\/strong><\/h2>\n\t\t\n<style>\n#text-1571559023 {\n  font-size: 0.75rem;\n  line-height: 3;\n  text-align: center;\n  color: rgb(0, 0, 0);\n}\n#text-1571559023 > * {\n  color: rgb(0, 0, 0);\n}\n<\/style>\n\t<\/div>\n\t\n\t<div id=\"text-2831635146\" class=\"text\">\n\t\t\n\n<p>Price: Rs.25<\/p>\n\t\t\n<style>\n#text-2831635146 {\n  text-align: center;\n  color: rgb(0, 0, 0);\n}\n#text-2831635146 > * {\n  color: rgb(0, 0, 0);\n}\n<\/style>\n\t<\/div>\n\t\n<a data-animate=\"bounceInUp\" rel=\"noopener noreferrer\" href=\"https:\/\/api.whatsapp.com\/send?phone=+923286060257&#038;text=Hello!%20Pind%20Da%20Zaika.%20Sir%20Simple%20Roti%20kr%20daee.\" target=\"_blank\" class=\"button success\"  style=\"border-radius:99px;\">\n    <span>Order Now<\/span>\n  <i class=\"icon-shopping-cart\" aria-hidden=\"true\" ><\/i><\/a>\n\n\n\n\t\t\t<\/div>\n\t\t<\/div>\n\t<\/div>\n\t\n\n\t\t<\/div>\n\t\t\t\t\t<\/div>\n\n\t\n\n\n<style>\n#row-1230008839 > .col > .col-inner {\n  background-color: #ffa500;\n  border-radius: 25px;\n}\n<\/style>\n<\/div>\n\n\t\t<\/div>\n\n\t\t\n<style>\n#section_1721477891 {\n  padding-top: 0px;\n  padding-bottom: 0px;\n  background-color: rgb(0,0,0);\n}\n#section_1721477891 .ux-shape-divider--top svg {\n  height: 150px;\n  --divider-top-width: 100%;\n}\n#section_1721477891 .ux-shape-divider--bottom svg {\n  height: 150px;\n  --divider-width: 100%;\n}\n<\/style>\n\t<\/section>\n\t\n\n","protected":false},"excerpt":{"rendered":"","protected":false},"author":1,"featured_media":0,"parent":0,"menu_order":0,"comment_status":"closed","ping_status":"closed","template":"","meta":{"footnotes":""},"_links":{"self":[{"href":"https:\/\/designer1.zarin.solutions\/index.php?rest_route=\/wp\/v2\/pages\/116"}],"collection":[{"href":"https:\/\/designer1.zarin.solutions\/index.php?rest_route=\/wp\/v2\/pages"}],"about":[{"href":"https:\/\/designer1.zarin.solutions\/index.php?rest_route=\/wp\/v2\/types\/page"}],"author":[{"embeddable":true,"href":"https:\/\/designer1.zarin.solutions\/index.php?rest_route=\/wp\/v2\/users\/1"}],"replies":[{"embeddable":true,"href":"https:\/\/designer1.zarin.solutions\/index.php?rest_route=%2Fwp%2Fv2%2Fcomments&post=116"}],"version-history":[{"count":5,"href":"https:\/\/designer1.zarin.solutions\/index.php?rest_route=\/wp\/v2\/pages\/116\/revisions"}],"predecessor-version":[{"id":594,"href":"https:\/\/designer1.zarin.solutions\/index.php?rest_route=\/wp\/v2\/pages\/116\/revisions\/594"}],"wp:attachment":[{"href":"https:\/\/designer1.zarin.solutions\/index.php?rest_route=%2Fwp%2Fv2%2Fmedia&parent=116"}],"curies":[{"name":"wp","href":"https:\/\/api.w.org\/{rel}","templated":true}]}}